{
  "products": [
    {
      "id": "001",
      "name": "Korean Snack",
      "description": "Authentic Korean snacks to enjoy at home",
      "price": "$19.99",
      "url": "https://amzn.to/4bubOGe",
      "category": "Food",
      "image": ""
    },
    {
      "id": "002",
      "name": "Bibigo Korean BBQ Flavor Seaweed Snack",
      "description": "Delicious Korean BBQ flavored seaweed snacks",
      "price": "$12.99",
      "url": "https://amzn.to/4qhhWVZ",
      "category": "Food",
      "image": ""
    },
    {
      "id": "003",
      "name": "Yakgwa Korean Sweet Tea Food Mini Honey",
      "description": "Traditional Korean honey cookies perfect for tea time",
      "price": "$15.99",
      "url": "https://amzn.to/3O5pcqu",
      "category": "Food",
      "image": ""
    },
    {
      "id": "004",
      "name": "Samyang Buldak Spicy Ramen Carbonara",
      "description": "Hot chicken ramen with carbonara flavor, Korean stir-fried instant noodle",
      "price": "$24.99",
      "url": "https://amzn.to/3MaZWi6",
      "category": "Food",
      "image": ""
    },
    {
      "id": "005",
      "name": "Buldak Tteokbokki 2Pack Korean Rice Cake (Cheese)",
      "description": "Instant Korean rice cake snack with cheese flavor",
      "price": "$18.99",
      "url": "https://amzn.to/4ae69Sg",
      "category": "Food",
      "image": ""
    },
    {
      "id": "006",
      "name": "ROUND LAB 1025 Dokdo Toner",
      "description": "Oil control facial toner with deep sea water for moisturization, Korean skin care",
      "price": "$22.99",
      "url": "https://amzn.to/4twhKFk",
      "category": "Beauty",
      "image": ""
    },
    {
      "id": "007",
      "name": "ROUND LAB 1025 Dokdo Cleanser",
      "description": "Low pH facial cleanser for sensitive skin with deep sea water, Korean skin care",
      "price": "$18.99",
      "url": "https://amzn.to/3M4Q09W",
      "category": "Beauty",
      "image": ""
    },
    {
      "id": "008",
      "name": "Ssamjang Korean Soybean Paste Sauce (Mild)",
      "description": "Korean flavor sauce for BBQ, lettuce wraps, rice, vegetables, and meat - O'food",
      "price": "$8.99",
      "url": "https://amzn.to/467PaA7",
      "category": "Food",
      "image": ""
    },
    {
      "id": "009",
      "name": "Korean Alphabet with Writing Workbook",
      "description": "Introductory guide to Hangeul series - Vol.1 Consonant and Vowel",
      "price": "$14.99",
      "url": "https://amzn.to/3Zgx6Qq",
      "category": "Culture",
      "image": ""
    },
    {
      "id": "010",
      "name": "Gochujang Korean Red Chili Paste (Mild)",
      "description": "Gluten-free spicy & sweet savory fermented sauce for bibimbap, marinades, stews & BBQ - O'food",
      "price": "$9.99",
      "url": "https://amzn.to/4r2Pkkw",
      "category": "Food",
      "image": ""
    },
    {
      "id": "011",
      "name": "Korean Ramen Cooking Pot",
      "description": "AHIER Korean ramen noodle pot with lid, spoon and chopsticks, fast heating cookware",
      "price": "$29.99",
      "url": "https://amzn.to/4qrpQMM",
      "category": "Shopping",
      "image": ""
    },
    {
      "id": "012",
      "name": "Polished Stainless Steel Spoons and Chopsticks Set",
      "description": "Korean chopsticks and spoons tableware with long-hand, reusable, set of 3-silver",
      "price": "$16.99",
      "url": "https://amzn.to/4qlWBLd",
      "category": "Shopping",
      "image": ""
    }
  ]
}
